extend_json.py
extend_json-0.0.2.dist-info/LICENSE
extend_json-0.0.2.dist-info/METADATA
extend_json-0.0.2.dist-info/WHEEL
extend_json-0.0.2.dist-info/top_level.txt
extend_json-0.0.2.dist-info/RECORD
