Metadata-Version: 2.1
Name: extend-json
Version: 0.0.2
Summary: additional methods for handling json files in python
Home-page: https://github.com/Schnilsibus/jsonExtended.git
Author: Nils Urbach
Author-email: ndu01u@gmail.com
License: MIT
Keywords: json,extended
Classifier: Development Status :: 3 - Alpha
Classifier: Intended Audience :: Developers
Classifier: License :: OSI Approved :: MIT License
Classifier: Operating System :: OS Independent
Classifier: Natural Language :: English
Classifier: Programming Language :: Python
Classifier: Topic :: Text Processing
Classifier: Topic :: Utilities
License-File: LICENSE
